qmorph.py
setup.py
qmorph.egg-info/PKG-INFO
qmorph.egg-info/SOURCES.txt
qmorph.egg-info/dependency_links.txt
qmorph.egg-info/top_level.txt