Metadata-Version: 1.1
Name: qmorph
Version: 0.1dev1
Summary: tabular data querying and pivoting with particular application to linguistic morphology
Home-page: http://github.com/jtauber/qmorph
Author: James Tauber
Author-email: jtauber@jtauber.com
License: MIT
Platform: UNKNOWN
Classifier: Intended Audience :: Developers
Classifier: License :: OSI Approved :: MIT License
Classifier: Operating System :: OS Independent
Classifier: Programming Language :: Python
